pysteamauth/__init__.py
pysteamauth/abstract/__init__.py
pysteamauth/abstract/request.py
pysteamauth/abstract/storage.py
pysteamauth/auth/__init__.py
pysteamauth/auth/schemas.py
pysteamauth/auth/steam.py
pysteamauth/base/__init__.py
pysteamauth/base/request.py
pysteamauth/base/storage.py
pysteamauth/errors/__init__.py
pysteamauth/errors/codes.py
pysteamauth/errors/exceptions.py
pysteamauth/errors/response.py
pysteamauth/pb2/__init__.py
pysteamauth/pb2/enums_pb2.py
pysteamauth/pb2/enums_pb2.pyi
pysteamauth/pb2/steammessages_base_pb2.py
pysteamauth/pb2/steammessages_auth/__init__.py
pysteamauth/pb2/steammessages_auth/steamclient_pb2.py
pysteamauth/pb2/steammessages_auth/steamclient_pb2.pyi
pysteamauth/pb2/steammessages_unified_base/__init__.py
pysteamauth/pb2/steammessages_unified_base/steamclient_pb2.py
pysteamauth2-1.1.7.dist-info/LICENSE
pysteamauth2-1.1.7.dist-info/METADATA
pysteamauth2-1.1.7.dist-info/WHEEL
pysteamauth2-1.1.7.dist-info/top_level.txt
pysteamauth2-1.1.7.dist-info/RECORD
