Metadata-Version: 2.2
Name: pysteamauth2
Version: 1.1.7
Summary: Asynchronous python library for Steam authorization using protobuf
Home-page: https://github.com/adiecho/pysteamauth
Author: Mike M / AdiEcho
Author-email: stopthisworldplease@outlook.com / adiecho@qq.com
License: MIT
Requires-Python: >=3.11
License-File: LICENSE
Requires-Dist: aiohttp==3.11.12
Requires-Dist: protobuf==5.29.3
Requires-Dist: pydantic==2.10.6
Requires-Dist: rsa==4.9
Requires-Dist: bitstring==4.3.0
Requires-Dist: urllib3==2.3.0
Dynamic: author
Dynamic: author-email
Dynamic: description
Dynamic: description-content-type
Dynamic: home-page
Dynamic: license
Dynamic: requires-dist
Dynamic: requires-python
Dynamic: summary
